[
    {
        "id": 1,
        "name": "Mozzarella Sticks",
        "description": "Crispy golden-fried mozzarella sticks served with marinara sauce.",
        "price": "199",
        "image_url": "https://res.cloudinary.com/dooxbo8sg/image/upload/v1745068730/Digital%20Diner/Appetizers/Mozzarella%20Sticks.jpg",
        "type": "Appetizer",
        "category": "Vegetarian",
        "is_vegan": false,
        "is_gluten_free": false,
        "spicy_level": 0
    },
    {
        "id": 2,
        "name": "Buffalo Wings",
        "description": "Spicy buffalo wings served with ranch or blue cheese dressing.",
        "price": "349",
        "image_url": "https://res.cloudinary.com/dooxbo8sg/image/upload/v1745068822/Digital%20Diner/Appetizers/Buffalo%20Wings.jpg",
        "type": "Appetizer",
        "category": "Non-Vegetarian",
        "is_vegan": false,
        "is_gluten_free": false,
        "spicy_level": 3
    },
    {
        "id": 3,
        "name": "Spring Rolls",
        "description": "Crispy vegetable spring rolls served with sweet chili sauce.",
        "price": "149",
        "image_url": "https://res.cloudinary.com/dooxbo8sg/image/upload/v1745068931/Digital%20Diner/Appetizers/Spring%20Rolls.webp",
        "type": "Appetizer",
        "category": "Vegan",
        "is_vegan": true,
        "is_gluten_free": false,
        "spicy_level": 1
    },
    {
        "id": 4,
        "name": "Garlic Bread",
        "description": "Toasted baguette slices topped with garlic butter and herbs.",
        "price": "129",
        "image_url": "https://res.cloudinary.com/dooxbo8sg/image/upload/v1745069085/Digital%20Diner/Appetizers/Garlic-Bread-5_lpuqx7.jpg",
        "type": "Appetizer",
        "category": "Vegetarian",
        "is_vegan": false,
        "is_gluten_free": false,
        "spicy_level": 0
    },
    {
        "id": 5,
        "name": "Stuffed Mushrooms",
        "description": "Mushroom caps stuffed with cheese, herbs, and breadcrumbs.",
        "price": "249",
        "image_url": "https://res.cloudinary.com/dooxbo8sg/image/upload/v1745069362/Digital%20Diner/Appetizers/stuffed-mushrooms_ctacxd.jpg",
        "type": "Appetizer",
        "category": "Vegetarian",
        "is_vegan": false,
        "is_gluten_free": true,
        "spicy_level": 0
    },
    {
        "id": 1,
        "name": "Chicken Biryani",
        "description": "Aromatic basmati rice cooked with tender chicken pieces and a blend of spices.",
        "price": "499",
        "image_url": "https://res.cloudinary.com/dooxbo8sg/image/upload/v1745071499/Digital%20Diner/Main%20Course/chicken-biryani_iwafbj.jpg",
        "type": "Main Course",
        "category": "Non-Vegetarian",
        "is_vegan": false,
        "is_gluten_free": false,
        "spicy_level": 3
    },
    {
        "id": 2,
        "name": "Paneer Butter Masala",
        "description": "Cottage cheese cubes cooked in a rich and creamy tomato-based gravy.",
        "price": "399",
        "image_url": "https://res.cloudinary.com/dooxbo8sg/image/upload/v1745071573/Digital%20Diner/Main%20Course/paneer-butter-masala-1_l379we.jpg",
        "type": "Main Course",
        "category": "Vegetarian",
        "is_vegan": false,
        "is_gluten_free": false,
        "spicy_level": 2
    },
    {
        "id": 3,
        "name": "Vegetable Biryani",
        "description": "Aromatic basmati rice cooked with mixed vegetables and a blend of spices.",
        "price": "399",
        "image_url": "https://res.cloudinary.com/dooxbo8sg/image/upload/v1745071642/Digital%20Diner/Main%20Course/vegetable-biryani-1_lpirdp.jpg",
        "type": "Main Course",
        "category": "Vegan",
        "is_vegan": true,
        "is_gluten_free": false,
        "spicy_level": 2
    },
    {
        "id": 4,
        "name": "Butter Chicken",
        "description": "Tender chicken pieces cooked in a rich and creamy tomato-based gravy.",
        "price": "549",
        "image_url": "https://res.cloudinary.com/dooxbo8sg/image/upload/v1745071746/Digital%20Diner/Main%20Course/Indian-butter-chicken-2_n4ahw3.jpg",
        "type": "Main Course",
        "category": "Non-Vegetarian",
        "is_vegan": false,
        "is_gluten_free": false,
        "spicy_level": 2
    },
    {
        "id": 5,
        "name": "Dal Tadka",
        "description": "Yellow lentils cooked with spices and tempered with ghee and cumin seeds.",
        "price": "199",
        "image_url": "https://res.cloudinary.com/dooxbo8sg/image/upload/v1745071930/Digital%20Diner/Main%20Course/dal-tadka_krh1wa.jpg",
        "type": "Main Course",
        "category": "Vegan",
        "is_vegan": true,
        "is_gluten_free": true,
        "spicy_level": 1
    },
    {
        "id": 1,
        "name": "Pavlova",
        "description": "A meringue-based dessert with a crisp crust and soft, light inside, topped with fresh fruits and whipped cream.",
        "price": "299",
        "image_url": "https://res.cloudinary.com/dooxbo8sg/image/upload/v1745072480/Digital%20Diner/Desserts/Mini-Pavlova25-1_e1rrhz.jpg",
        "type": "Dessert",
        "category": "Vegetarian",
        "is_vegan": false,
        "is_gluten_free": true,
        "spicy_level": 0
    },
    {
        "id": 2,
        "name": "Panna Cotta",
        "description": "An Italian dessert of sweetened cream thickened with gelatin and molded, often served with berry coulis.",
        "price": "399",
        "image_url": "https://res.cloudinary.com/dooxbo8sg/image/upload/v1745072579/Digital%20Diner/Desserts/Panna-cotta-recipe-4_phpthc.jpg",
        "type": "Dessert",
        "category": "Vegetarian",
        "is_vegan": false,
        "is_gluten_free": true,
        "spicy_level": 0
    },
    {
        "id": 3,
        "name": "Knafeh",
        "description": "A Middle Eastern dessert made of spun pastry dough layered with cheese and soaked in a sweet syrup.",
        "price": "499",
        "image_url": "https://res.cloudinary.com/dooxbo8sg/image/upload/v1745072655/Digital%20Diner/Desserts/knafeh-1-scaled_rawrrc.jpg",
        "type": "Dessert",
        "category": "Vegetarian",
        "is_vegan": false,
        "is_gluten_free": false,
        "spicy_level": 0
    },
    {
        "id": 4,
        "name": "Bananas Foster",
        "description": "A New Orleans dessert made with cooked bananas in a butter, brown sugar, and rum sauce, often flambéed.",
        "price": "399",
        "image_url": "https://res.cloudinary.com/dooxbo8sg/image/upload/v1745072775/Digital%20Diner/Desserts/mla102583_0207_bananas02_vert-5dc1f485f99e469b8223512506dfb053_kmq79d.jpg",
        "type": "Dessert",
        "category": "Non-Vegetarian",
        "is_vegan": false,
        "is_gluten_free": true,
        "spicy_level": 0
    },
    {
        "id": 5,
        "name": "Carrot Cake",
        "description": "A moist spiced cake made with grated carrots, often topped with cream cheese frosting.",
        "price": "299",
        "image_url": "https://res.cloudinary.com/dooxbo8sg/image/upload/v1745072831/Digital%20Diner/Desserts/images_gnp9sx.jpg",
        "type": "Dessert",
        "category": "Vegetarian",
        "is_vegan": false,
        "is_gluten_free": false,
        "spicy_level": 1
    },
    {
        "id": 1,
        "name": "Lassi",
        "description": "A refreshing yogurt-based drink, often flavored with mango, rose, or saffron, and served chilled.",
        "price": "150",
        "image_url": "https://res.cloudinary.com/dooxbo8sg/image/upload/v1745074457/Digital%20Diner/Lassi/yogurt-drink-p2_yx0b1j.jpg",
        "type": "Drink",
        "category": "Dairy",
        "is_vegan": false,
        "is_gluten_free": true,
        "spicy_level": 0
    },
    {
        "id": 2,
        "name": "Masala Chai",
        "description": "A spiced tea brewed with black tea leaves, milk, sugar, and a blend of aromatic spices like cardamom, cinnamon, and ginger.",
        "price": "50",
        "image_url": "https://res.cloudinary.com/dooxbo8sg/image/upload/v1745074662/Digital%20Diner/Lassi/Authentic-Chai-Recipe-100_e1zxlm.jpg",
        "type": "Drink",
        "category": "Tea",
        "is_vegan": false,
        "is_gluten_free": true,
        "spicy_level": 2
    },
    {
        "id": 3,
        "name": "Jal Jeera",
        "description": "A tangy and spicy drink made from cumin, ginger, black pepper, mint, and tamarind, often served as an appetizer.",
        "price": "80",
        "image_url": "https://res.cloudinary.com/dooxbo8sg/image/upload/v1745074994/Digital%20Diner/Lassi/jal-jeera-cumin-water-beverage-appetizer-indian-flavored-spice-mix-known-as-powder-hindi-means-base-366587504_snpfmm.jpg",
        "type": "Drink",
        "category": "Spiced",
        "is_vegan": true,
        "is_gluten_free": true,
        "spicy_level": 3
    },
    {
        "id": 4,
        "name": "Aam Panna",
        "description": "A refreshing summer drink made from raw mangoes, sugar, and spices like cumin and black salt, known for its cooling properties.",
        "price": "120",
        "image_url": "https://res.cloudinary.com/dooxbo8sg/image/upload/v1745075071/Digital%20Diner/Lassi/aam-panna-recipe-1_obl6bn.jpg",
        "type": "Drink",
        "category": "Fruit-based",
        "is_vegan": true,
        "is_gluten_free": true,
        "spicy_level": 1
    },
    {
        "id": 5,
        "name": "Thandai",
        "description": "A milk-based drink flavored with almonds, fennel seeds, rose petals, cardamom, saffron, and sugar, traditionally consumed during festivals.",
        "price": "200",
        "image_url": "https://res.cloudinary.com/dooxbo8sg/image/upload/v1745075112/Digital%20Diner/Lassi/Thandai-recipe_palates-desire-2_t9dzxn.jpg",
        "type": "Drink",
        "category": "Milk-based",
        "is_vegan": false,
        "is_gluten_free": true,
        "spicy_level": 1
    }
]